ricoh_ldap_sync
