Metadata-Version: 2.1
Name: ricoh-ldap-sync
Version: 0.1.1
Summary: For creating a CSV file for Ricoh copiers from information in LDAP
Home-page: https://github.com/phistrom/ricoh-ldap-sync
Author: Phillip Stromberg
Author-email: phillip@strombergs.com
License: MIT
Platform: UNKNOWN
Classifier: Development Status :: 4 - Beta
Classifier: Intended Audience :: System Administrators
Classifier: Natural Language :: English
Classifier: License :: OSI Approved :: MIT License
Classifier: Programming Language :: Python
Classifier: Programming Language :: Python :: 3
Classifier: Programming Language :: Python :: 3.5
Classifier: Programming Language :: Python :: 3.6
Classifier: Programming Language :: Python :: 3.7
